memos/__init__.py
memos/api/client.py
memos/api/config.py
memos/api/context/dependencies.py
memos/api/exceptions.py
memos/api/handlers/__init__.py
memos/api/handlers/add_handler.py
memos/api/handlers/base_handler.py
memos/api/handlers/chat_handler.py
memos/api/handlers/component_init.py
memos/api/handlers/config_builders.py
memos/api/handlers/feedback_handler.py
memos/api/handlers/formatters_handler.py
memos/api/handlers/memory_handler.py
memos/api/handlers/scheduler_handler.py
memos/api/handlers/search_handler.py
memos/api/handlers/suggestion_handler.py
memos/api/mcp_serve.py
memos/api/middleware/request_context.py
memos/api/product_api.py
memos/api/product_models.py
memos/api/routers/__init__.py
memos/api/routers/product_router.py
memos/api/routers/server_router.py
memos/api/server_api.py
memos/api/start_api.py
memos/chunkers/__init__.py
memos/chunkers/base.py
memos/chunkers/charactertext_chunker.py
memos/chunkers/factory.py
memos/chunkers/markdown_chunker.py
memos/chunkers/sentence_chunker.py
memos/chunkers/simple_chunker.py
memos/cli.py
memos/configs/__init__.py
memos/configs/base.py
memos/configs/chunker.py
memos/configs/embedder.py
memos/configs/graph_db.py
memos/configs/internet_retriever.py
memos/configs/llm.py
memos/configs/mem_agent.py
memos/configs/mem_chat.py
memos/configs/mem_cube.py
memos/configs/mem_os.py
memos/configs/mem_reader.py
memos/configs/mem_scheduler.py
memos/configs/mem_user.py
memos/configs/memory.py
memos/configs/parser.py
memos/configs/reranker.py
memos/configs/utils.py
memos/configs/vec_db.py
memos/context/context.py
memos/dependency.py
memos/deprecation.py
memos/embedders/__init__.py
memos/embedders/ark.py
memos/embedders/base.py
memos/embedders/factory.py
memos/embedders/ollama.py
memos/embedders/sentence_transformer.py
memos/embedders/universal_api.py
memos/exceptions.py
memos/extras/__init__.py
memos/extras/nli_model/__init__.py
memos/extras/nli_model/client.py
memos/extras/nli_model/server/README.md
memoryos-2.0.4.dist-info/METADATA
memoryos-2.0.4.dist-info/WHEEL
memoryos-2.0.4.dist-info/entry_points.txt
memoryos-2.0.4.dist-info/licenses/LICENSE
memoryos-2.0.4.dist-info/RECORD
