Metadata-Version: 2.4
Name: MemoryOS
Version: 2.0.4
Summary: Intelligence Begins with Memory
License: Apache-2.0
License-File: LICENSE
Keywords: memory,llm,language model,memoryOS,agent,kv cache,lora
Author: MemTensor
Author-email: MemTensor@memtensor.cn
Requires-Python: >=3.10
Classifier: Intended Audience :: Developers
Classifier: License :: OSI Approved :: Apache Software License
Classifier: Natural Language :: English
Classifier: Natural Language :: Chinese (Simplified)
Classifier: Operating System :: OS Independent
Classifier: Programming Language :: Python :: 3 :: Only
Classifier: Programming Language :: Python :: 3.10
Classifier: Programming Language :: Python :: 3.11
Classifier: Programming Language :: Python :: 3.12
Classifier: Programming Language :: Python :: 3.13
Classifier: Topic :: Software Development :: Libraries
Classifier: Topic :: Software Development :: Libraries :: Python Modules
Provides-Extra: all
Provides-Extra: mem-reader
Provides-Extra: mem-scheduler
Provides-Extra: mem-user
Provides-Extra: pref-mem
Provides-Extra: skill-mem
Provides-Extra: tree-mem
Requires-Dist: alibabacloud-oss-v2 (>=1.2.2,<1.2.3) ; extra == "all"
Requires-Dist: alibabacloud-oss-v2 (>=1.2.2,<1.2.3) ; extra == "skill-mem"
Requires-Dist: cachetools (>=6.0.0) ; extra == "all"
Requires-Dist: chonkie (>=1.0.7,<2.0.0) ; extra == "all"
Requires-Dist: chonkie (>=1.0.7,<2.0.0) ; extra == "mem-reader"
Requires-Dist: concurrent-log-handler (>=0.9.28,<1.0.0)
Requires-Dist: datasketch (>=1.6.5,<2.0.0) ; extra == "all"
Requires-Dist: datasketch (>=1.6.5,<2.0.0) ; extra == "pref-mem"
Requires-Dist: fastapi[all] (>=0.115.12,<0.116.0)
Requires-Dist: fastmcp (>=2.10.5,<3.0.0)
Requires-Dist: jieba (>=0.38.1,<0.42.1) ; extra == "all"
Requires-Dist: langchain-text-splitters (>=1.0.0,<2.0.0) ; extra == "all"
Requires-Dist: langchain-text-splitters (>=1.0.0,<2.0.0) ; extra == "mem-reader"
Requires-Dist: markitdown[docx,pdf,pptx,xls,xlsx] (>=0.1.1,<0.2.0) ; extra == "all"
Requires-Dist: markitdown[docx,pdf,pptx,xls,xlsx] (>=0.1.1,<0.2.0) ; extra == "mem-reader"
Requires-Dist: neo4j (>=5.28.1,<6.0.0) ; extra == "all"
Requires-Dist: neo4j (>=5.28.1,<6.0.0) ; extra == "tree-mem"
Requires-Dist: nltk (>=3.9.1,<4.0.0) ; extra == "all"
Requires-Dist: ollama (>=0.5.0,<0.5.1)
Requires-Dist: openai (>=1.77.0,<2.0.0)
Requires-Dist: pika (>=1.3.2,<2.0.0) ; extra == "all"
Requires-Dist: pika (>=1.3.2,<2.0.0) ; extra == "mem-scheduler"
Requires-Dist: prometheus-client (>=0.23.1,<0.24.0)
Requires-Dist: pymilvus (>=2.5.12,<3.0.0) ; extra == "pref-mem"
Requires-Dist: pymilvus (>=2.6.1,<3.0.0) ; extra == "all"
Requires-Dist: pymysql (>=1.1.0,<2.0.0)
Requires-Dist: pymysql (>=1.1.0,<2.0.0) ; extra == "all"
Requires-Dist: pymysql (>=1.1.0,<2.0.0) ; extra == "mem-user"
Requires-Dist: python-dateutil (>=2.9.0.post0,<3.0.0)
Requires-Dist: qdrant-client (>=1.16.0,<2.0.0) ; extra == "all"
Requires-Dist: rake-nltk (>=1.0.6,<1.1.0) ; extra == "all"
Requires-Dist: rank-bm25 (>=0.2.2) ; extra == "all"
Requires-Dist: redis (>=6.2.0,<7.0.0) ; extra == "all"
Requires-Dist: redis (>=6.2.0,<7.0.0) ; extra == "mem-scheduler"
Requires-Dist: schedule (>=1.2.2,<2.0.0) ; extra == "all"
Requires-Dist: schedule (>=1.2.2,<2.0.0) ; extra == "tree-mem"
Requires-Dist: scikit-learn (>=1.7.0,<2.0.0)
Requires-Dist: sentence-transformers (>=4.1.0,<5.0.0) ; extra == "all"
Requires-Dist: sqlalchemy (>=2.0.41,<3.0.0)
Requires-Dist: tenacity (>=9.1.2,<10.0.0)
Requires-Dist: torch (>=2.7.1,<3.0.0) ; extra == "all"
Requires-Dist: transformers (>=4.51.3,<5.0.0)
Requires-Dist: volcengine-python-sdk (>=4.0.4,<5.0.0) ; extra == "all"
Project-URL: Documentation, https://memos-docs.openmem.net/home/overview/
Project-URL: Homepage, https://memos.openmem.net/
Project-URL: Repository, https://github.com/MemTensor/MemOS
Project-URL: changelog, https://github.com/MemTensor/MemOS/releases
Project-URL: download, https://pypi.org/project/MemoryOS/#files
Project-URL: issues, https://github.com/MemTensor/MemOS/issues
Project-URL: releasenotes, https://github.com/MemTensor/MemOS/releases
